magnumclient/__init__.py
magnumclient/client.py
magnumclient/exceptions.py
magnumclient/i18n.py
magnumclient/shell.py
magnumclient/version.py
magnumclient/common/__init__.py
magnumclient/common/base.py
magnumclient/common/cliutils.py
magnumclient/common/httpclient.py
magnumclient/common/utils.py
magnumclient/common/apiclient/__init__.py
magnumclient/common/apiclient/base.py
magnumclient/common/apiclient/exceptions.py
magnumclient/osc/__init__.py
magnumclient/osc/plugin.py
magnumclient/osc/v1/__init__.py
magnumclient/osc/v1/certificates.py
magnumclient/osc/v1/cluster_templates.py
magnumclient/osc/v1/clusters.py
magnumclient/osc/v1/credentials.py
magnumclient/osc/v1/mservices.py
magnumclient/osc/v1/nodegroups.py
magnumclient/osc/v1/quotas.py
magnumclient/osc/v1/stats.py
magnumclient/tests/__init__.py
magnumclient/tests/base.py
magnumclient/tests/test_client.py
magnumclient/tests/test_httpclient.py
magnumclient/tests/test_magnumclient.py
magnumclient/tests/test_utils.py
magnumclient/tests/utils.py
magnumclient/tests/osc/__init__.py
magnumclient/tests/osc/unit/__init__.py
magnumclient/tests/osc/unit/osc_fakes.py
magnumclient/tests/osc/unit/osc_utils.py
magnumclient/tests/osc/unit/v1/__init__.py
magnumclient/tests/osc/unit/v1/fakes.py
magnumclient/tests/osc/unit/v1/test_certificates.py
magnumclient/tests/osc/unit/v1/test_cluster_templates.py
magnumclient/tests/osc/unit/v1/test_clusters.py
magnumclient/tests/osc/unit/v1/test_mservices.py
magnumclient/tests/osc/unit/v1/test_nodegroups.py
magnumclient/tests/osc/unit/v1/test_quotas.py
magnumclient/tests/osc/unit/v1/test_stats.py
magnumclient/tests/test_csr/test.csr
magnumclient/tests/v1/__init__.py
magnumclient/tests/v1/shell_test_base.py
magnumclient/tests/v1/test_certificates.py
magnumclient/tests/v1/test_certificates_shell.py
magnumclient/tests/v1/test_client.py
magnumclient/tests/v1/test_clusters.py
magnumclient/tests/v1/test_clusters_shell.py
magnumclient/tests/v1/test_clustertemplates.py
python_magnumclient-4.9.0.dist-info/AUTHORS
python_magnumclient-4.9.0.dist-info/LICENSE
python_magnumclient-4.9.0.dist-info/METADATA
python_magnumclient-4.9.0.dist-info/WHEEL
python_magnumclient-4.9.0.dist-info/entry_points.txt
python_magnumclient-4.9.0.dist-info/pbr.json
python_magnumclient-4.9.0.dist-info/top_level.txt
python_magnumclient-4.9.0.dist-info/RECORD
