Metadata-Version: 2.1
Name: python-magnumclient
Version: 4.9.0
Summary: Client library for Magnum API
Home-page: https://docs.openstack.org/python-magnumclient/latest/
Author: OpenStack
Author-email: openstack-discuss@lists.openstack.org
Classifier: Environment :: OpenStack
Classifier: Intended Audience :: Information Technology
Classifier: Intended Audience :: System Administrators
Classifier: License :: OSI Approved :: Apache Software License
Classifier: Operating System :: POSIX :: Linux
Classifier: Programming Language :: Python
Classifier: Programming Language :: Python :: Implementation :: CPython
Classifier: Programming Language :: Python :: 3 :: Only
Classifier: Programming Language :: Python :: 3
Classifier: Programming Language :: Python :: 3.8
Classifier: Programming Language :: Python :: 3.9
Classifier: Programming Language :: Python :: 3.10
Classifier: Programming Language :: Python :: 3.11
Requires-Python: >=3.8
License-File: LICENSE
Requires-Dist: pbr!=2.1.0,>=2.0.0
Requires-Dist: keystoneauth1>=3.4.0
Requires-Dist: stevedore>=1.20.0
Requires-Dist: requests>=2.14.2
Requires-Dist: oslo.i18n>=3.15.3
Requires-Dist: oslo.log>=3.36.0
Requires-Dist: oslo.serialization!=2.19.1,>=2.18.0
Requires-Dist: oslo.utils>=3.33.0
Requires-Dist: openstacksdk>=0.10.0
Requires-Dist: osc-lib>=1.8.0
Requires-Dist: PrettyTable>=0.7.2
Requires-Dist: cryptography>=3.0
Requires-Dist: decorator>=3.4.0
